{
	"credit": "Made with Blockbench",
	"ambientocclusion": false,
	"texture_size": [64, 128],
	"textures": {
		"1": "rampantskies:block/exhaust_texture"
	},
	"elements": [
		{
			"from": [8, 2, -15.28884],
			"to": [8, 14, 9.71116],
			"rotation": {"angle": 0, "axis": "y", "origin": [7.75, 8.03884, 12.46116]},
			"faces": {
				"north": {"uv": [10, 5, 13, 6.5], "rotation": 90, "texture": "#1"},
				"east": {"uv": [12.5, 6.5, 6.25, 8], "texture": "#1"},
				"south": {"uv": [13, 5, 16, 6.5], "rotation": 270, "texture": "#1"},
				"west": {"uv": [16, 1.5, 9.75, 0], "rotation": 180, "texture": "#1"},
				"up": {"uv": [0, 0, 6.25, 1.5], "rotation": 270, "texture": "#1"},
				"down": {"uv": [0, 6.5, 6.25, 8], "rotation": 270, "texture": "#1"}
			}
		},
		{
			"from": [8.001, 1, 2],
			"to": [8.001, 15, 16],
			"rotation": {"angle": 0, "axis": "y", "origin": [7.75, 8.03884, 12.46116]},
			"faces": {
				"north": {"uv": [6.25, 3.25, 9.75, 5], "rotation": 90, "texture": "#1"},
				"east": {"uv": [6.25, 3.25, 2.75, 5], "texture": "#1"},
				"south": {"uv": [9.75, 1.5, 13.25, 3.25], "rotation": 270, "texture": "#1"},
				"west": {"uv": [13.25, 5, 9.75, 3.25], "rotation": 180, "texture": "#1"},
				"up": {"uv": [2.75, 1.5, 6.25, 3.25], "rotation": 270, "texture": "#1"},
				"down": {"uv": [6.25, 1.5, 9.75, 3.25], "rotation": 270, "texture": "#1"}
			}
		},
		{
			"from": [8.25, 2.1, -15.28884],
			"to": [8.25, 14.1, 9.71116],
			"rotation": {"angle": -45, "axis": "z", "origin": [8, 8.13884, 12.46116]},
			"faces": {
				"north": {"uv": [10, 5, 13, 6.5], "rotation": 90, "texture": "#1"},
				"east": {"uv": [12.5, 6.5, 6.25, 8], "texture": "#1"},
				"south": {"uv": [13, 5, 16, 6.5], "rotation": 270, "texture": "#1"},
				"west": {"uv": [16, 1.5, 9.75, 0], "rotation": 180, "texture": "#1"},
				"up": {"uv": [0, 0, 6.25, 1.5], "rotation": 270, "texture": "#1"},
				"down": {"uv": [0, 6.5, 6.25, 8], "rotation": 270, "texture": "#1"}
			}
		},
		{
			"from": [8.251, 1.1, 2],
			"to": [8.251, 15.1, 16],
			"rotation": {"angle": -45, "axis": "z", "origin": [8, 8.13884, 12.46116]},
			"faces": {
				"north": {"uv": [6.25, 3.25, 9.75, 5], "rotation": 90, "texture": "#1"},
				"east": {"uv": [6.25, 3.25, 2.75, 5], "texture": "#1"},
				"south": {"uv": [9.75, 1.5, 13.25, 3.25], "rotation": 270, "texture": "#1"},
				"west": {"uv": [13.25, 5, 9.75, 3.25], "rotation": 180, "texture": "#1"},
				"up": {"uv": [2.75, 1.5, 6.25, 3.25], "rotation": 270, "texture": "#1"},
				"down": {"uv": [6.25, 1.5, 9.75, 3.25], "rotation": 270, "texture": "#1"}
			}
		},
		{
			"from": [1.71116, 7.78884, -15.28884],
			"to": [13.71116, 7.78884, 9.71116],
			"rotation": {"angle": 0, "axis": "z", "origin": [7.75, 8.03884, 12.46116]},
			"faces": {
				"north": {"uv": [10, 5, 13, 6.5], "texture": "#1"},
				"east": {"uv": [0, 0, 6.25, 1.5], "texture": "#1"},
				"south": {"uv": [13, 5, 16, 6.5], "texture": "#1"},
				"west": {"uv": [0, 6.5, 6.25, 8], "texture": "#1"},
				"up": {"uv": [16, 1.5, 9.75, 0], "rotation": 270, "texture": "#1"},
				"down": {"uv": [12.5, 6.5, 6.25, 8], "rotation": 90, "texture": "#1"}
			}
		},
		{
			"from": [0.71116, 7.78784, 2],
			"to": [14.71116, 7.78784, 16],
			"rotation": {"angle": 0, "axis": "z", "origin": [7.75, 8.03884, 12.46116]},
			"faces": {
				"north": {"uv": [6.25, 3.25, 9.75, 5], "texture": "#1"},
				"east": {"uv": [2.75, 1.5, 6.25, 3.25], "texture": "#1"},
				"south": {"uv": [9.75, 1.5, 13.25, 3.25], "texture": "#1"},
				"west": {"uv": [6.25, 1.5, 9.75, 3.25], "texture": "#1"},
				"up": {"uv": [13.25, 5, 9.75, 3.25], "rotation": 270, "texture": "#1"},
				"down": {"uv": [6.25, 3.25, 2.75, 5], "rotation": 90, "texture": "#1"}
			}
		},
		{
			"from": [1.96116, 7.88884, -15.28884],
			"to": [13.96116, 7.88884, 9.71116],
			"rotation": {"angle": -45, "axis": "z", "origin": [8, 8.13884, 12.46116]},
			"faces": {
				"north": {"uv": [10, 5, 13, 6.5], "texture": "#1"},
				"east": {"uv": [0, 0, 6.25, 1.5], "texture": "#1"},
				"south": {"uv": [13, 5, 16, 6.5], "texture": "#1"},
				"west": {"uv": [0, 6.5, 6.25, 8], "texture": "#1"},
				"up": {"uv": [16, 1.5, 9.75, 0], "rotation": 270, "texture": "#1"},
				"down": {"uv": [12.5, 6.5, 6.25, 8], "rotation": 90, "texture": "#1"}
			}
		},
		{
			"from": [0.96116, 7.88784, 2],
			"to": [14.96116, 7.88784, 16],
			"rotation": {"angle": -45, "axis": "z", "origin": [8, 8.13884, 12.46116]},
			"faces": {
				"north": {"uv": [6.25, 3.25, 9.75, 5], "texture": "#1"},
				"east": {"uv": [2.75, 1.5, 6.25, 3.25], "texture": "#1"},
				"south": {"uv": [9.75, 1.5, 13.25, 3.25], "texture": "#1"},
				"west": {"uv": [6.25, 1.5, 9.75, 3.25], "texture": "#1"},
				"up": {"uv": [13.25, 5, 9.75, 3.25], "rotation": 270, "texture": "#1"},
				"down": {"uv": [6.25, 3.25, 2.75, 5], "rotation": 90, "texture": "#1"}
			}
		}
	]
}